logspot/__init__.py
logspot/alerting.py
logspot/blueprint.py
logspot/fastapi_blueprint.py
logspot/manager.py
logspot-0.4.0.dist-info/METADATA
logspot-0.4.0.dist-info/WHEEL
logspot-0.4.0.dist-info/top_level.txt
logspot-0.4.0.dist-info/RECORD
