Metadata-Version: 2.4
Name: logspot
Version: 0.4.0
Summary: Reusable /logs route + logging manager for Flask and FastAPI apps
Home-page: https://github.com/rishabhpandey106/logspot
Author: Rishabh Kumar Pandey
Author-email: rishabhpandey230@gmail.com
Keywords: flask,fastapi,logs,logging,flask-logging,fastapi-logging,logspot
Classifier: Programming Language :: Python :: 3
Classifier: Framework :: Flask
Classifier: Framework :: FastAPI
Classifier: License :: OSI Approved :: MIT License
Classifier: Operating System :: OS Independent
Requires-Python: >=3.8
Requires-Dist: Flask>=2.0.0
Requires-Dist: fastapi>=0.95.0
Requires-Dist: uvicorn>=0.20.0
Requires-Dist: requests>=2.0.0
Dynamic: author
Dynamic: author-email
Dynamic: classifier
Dynamic: description
Dynamic: description-content-type
Dynamic: home-page
Dynamic: keywords
Dynamic: requires-dist
Dynamic: requires-python
Dynamic: summary
